# Задача 1
### Формулировка задачи
Исследование виртуальной стековой машины CPython.

Изучите возможности просмотра байткода ВМ CPython.

```Python
import dis

def foo(x):
    while x:
        x -= 1
    return x + 1

print(dis.dis(foo))
```
Опишите по шагам, что делает каждая из следующих команд (приведите эквивалентное выражение на Python):

11 0 LOAD_FAST 0 (x) 2 LOAD_CONST 1 (10) 4 BINARY_MULTIPLY 6 LOAD_CONST 2 (42) 8 BINARY_ADD 10 RETURN_VALUE

### Решение
1. `0 LOAD_FAST 0 (x)` - Загружает значение переменной x из локальной области. Это эквивалент получения значения переменной в Python.
```Python 
x
```
2. `2 LOAD_CONST 1 (10)` - Загружает константное значение 10 в стек.
```Python
10
```
3. `4 BINARY_MULTIPLY` - Извлекает два верхних элемента из стека (в данном случае, значение переменной x и константу 10) и выполняет операцию умножения, результат помещает обратно в стек.
```Python
x * 10
```
4. `6 LOAD_CONST 2 (42)` - Загружает константное значение 42 в стек.
```Python
42
```
5. `8 BINARY_ADD` - Извлекает два верхних элемента из стека (результат умножения и константу 42) и выполняет операцию сложения, результат помещает обратно в стек.
```Python
(x * 10) + 42
```
6. `10 RETURN_VALUE` - Возвращает верхнее значение из стека в качестве результата функции и завершает её выполнение.
```Python
return (x * 10) + 42
```
Полный эквивалент на Python:
```Python
def foo(x):
    return (x * 10) + 42
```
Данный байткод представляет функцию, которая принимает параметр x, умножает его на 10, добавляет 42 и возвращает результат.

# Задача 2
### Формулировка задачи

Что делает следующий байткод (опишите шаги его работы)? Это известная функция, назовите ее.
```
  5           0 LOAD_CONST               1 (1)
              2 STORE_FAST               1 (r)

  6     >>    4 LOAD_FAST                0 (n)
              6 LOAD_CONST               1 (1)
              8 COMPARE_OP               4 (>)
             10 POP_JUMP_IF_FALSE       30

  7          12 LOAD_FAST                1 (r)
             14 LOAD_FAST                0 (n)
             16 INPLACE_MULTIPLY
             18 STORE_FAST               1 (r)

  8          20 LOAD_FAST                0 (n)
             22 LOAD_CONST               1 (1)
             24 INPLACE_SUBTRACT
             26 STORE_FAST               0 (n)
             28 JUMP_ABSOLUTE            4

  9     >>   30 LOAD_FAST                1 (r)
             32 RETURN_VALUE
```

### Решение
1. `0 LOAD_CONST 1 (1)` - Загружает константу 1 в стек.
2. `2 STORE_FAST 1 (r)` - Сохраняет значение 1 в локальной переменной r.
3. `4 LOAD_FAST 0 (n)` - Загружает значение переменной n из локальной области в стек.
4. `6 LOAD_CONST 1 (1)` - Загружает константу 1 в стек.
5. `8 COMPARE_OP 4 (>)` - Сравнивает значение n с 1. Проверяет, больше ли n единицы.
6. `10 POP_JUMP_IF_FALSE 30` - Если результат сравнения False (то есть n не больше 1), выполняется переход на инструкцию с индексом 30 (выход из цикла). Иначе продолжает выполнение следующих команд.
